KratosMultiphysics/ConvectionDiffusionApplication/__init__.py
KratosMultiphysics/ConvectionDiffusionApplication/__init__.pyi
KratosMultiphysics/ConvectionDiffusionApplication/adjoint_diffusion_solver.py
KratosMultiphysics/ConvectionDiffusionApplication/apply_thermal_face_process.py
KratosMultiphysics/ConvectionDiffusionApplication/conjugate_heat_transfer_solver.py
KratosMultiphysics/ConvectionDiffusionApplication/convection_diffusion_analysis.py
KratosMultiphysics/ConvectionDiffusionApplication/convection_diffusion_explicit_solver.py
KratosMultiphysics/ConvectionDiffusionApplication/convection_diffusion_semi_eulerian_solver.py
KratosMultiphysics/ConvectionDiffusionApplication/convection_diffusion_solver.py
KratosMultiphysics/ConvectionDiffusionApplication/convection_diffusion_stationary_embedded_solver.py
KratosMultiphysics/ConvectionDiffusionApplication/convection_diffusion_stationary_matrix_solver.py
KratosMultiphysics/ConvectionDiffusionApplication/convection_diffusion_stationary_shifted_boundary_solver.py
KratosMultiphysics/ConvectionDiffusionApplication/convection_diffusion_stationary_solver.py
KratosMultiphysics/ConvectionDiffusionApplication/convection_diffusion_transient_solver.py
KratosMultiphysics/ConvectionDiffusionApplication/coupled_fluid_thermal_solver.py
KratosMultiphysics/ConvectionDiffusionApplication/coupled_structural_thermal_solver.py
KratosMultiphysics/ConvectionDiffusionApplication/move_particle_utility_process.py
KratosMultiphysics/ConvectionDiffusionApplication/python_solvers_wrapper_convection_diffusion.py
KratosMultiphysics/ConvectionDiffusionApplication/response_functions/__init__.py
KratosMultiphysics/ConvectionDiffusionApplication/response_functions/convection_diffusion_response.py
KratosMultiphysics/ConvectionDiffusionApplication/response_functions/convection_diffusion_response_function_factory.py
KratosMultiphysics/.libs/KratosConvectionDiffusionApplication.cpython-313-x86_64-linux-gnu.so
kratosconvectiondiffusionapplication-10.4.0.dist-info/METADATA
kratosconvectiondiffusionapplication-10.4.0.dist-info/WHEEL
kratosconvectiondiffusionapplication-10.4.0.dist-info/RECORD
